clus/__init__.py
clus/main.py
clus/src/__init__.py
clus/src/core/__init__.py
clus/src/core/analysis.py
clus/src/core/cluster_initialization.py
clus/src/core/data_loading.py
clus/src/core/handle_empty_clusters.py
clus/src/core/hungarian_algorithm.py
clus/src/core/normalization.py
clus/src/core/saving_path.py
clus/src/core/visualisation.py
clus/src/core/evaluation_metric/__init__.py
clus/src/core/evaluation_metric/adjusted_rand_index.py
clus/src/core/evaluation_metric/evaluation_metric.py
clus/src/core/methods/__init__.py
clus/src/core/methods/methods.py
clus/src/core/methods/minibatch_kmeans.py
clus/src/core/methods/density_based/__init__.py
clus/src/core/methods/density_based/dbclasd.py
clus/src/core/methods/density_based/dbscan.py
clus/src/core/methods/density_based/optics.py
clus/src/core/methods/iterative/__init__.py
clus/src/core/methods/iterative/fuzzy_c_means_select.py
clus/src/core/methods/iterative/linearized_fuzzy_c_medoids_select.py
clus/src/core/methods/partition_based/__init__.py
clus/src/core/methods/partition_based/fuzzy_c_means.py
clus/src/core/methods/partition_based/fuzzy_c_medoids.py
clus/src/core/methods/partition_based/hard_c_medoids.py
clus/src/core/methods/partition_based/kmeans.py
clus/src/core/methods/partition_based/linearized_fuzzy_c_medoids.py
clus/src/utils/__init__.py
clus/src/utils/array.py
clus/src/utils/click.py
clus/src/utils/common.py
clus/src/utils/decorator.py
clus/src/utils/distance_matrix.py
clus/src/utils/process.py
clus/src/utils/random.py
clus/src/utils/time.py
clus/test/__init__.py
clus/test/dataset.py
clus/test/test_sklearn_kmeans_iris.py
clus/test/methods/__init__.py
clus/test/methods/fuzzy_c_means.py
clus/test/methods/fuzzy_c_means_select.py
clus/test/methods/fuzzy_c_medoids.py
clus-0.0.2.dist-info/METADATA
clus-0.0.2.dist-info/WHEEL
clus-0.0.2.dist-info/entry_points.txt
clus-0.0.2.dist-info/top_level.txt
clus-0.0.2.dist-info/RECORD
